distribution_checker/__init__.py
distribution_checker/main.py
distribution_checker-0.1.2.dist-info/METADATA
distribution_checker-0.1.2.dist-info/WHEEL
distribution_checker-0.1.2.dist-info/licenses/LICENSE
distribution_checker-0.1.2.dist-info/RECORD
