Metadata-Version: 2.1
Name: Distribution_Checker
Version: 0.1.2
Summary: Python Distribution Checker for Pandas datas using Scipy package
Project-URL: Homepage, https://github.com/amirhr098/Distribution-Checker
Project-URL: Bug Tracker, https://github.com/amirhr098/Distribution-Checker/issues
Author-email: Amir Hosein Rasouli <amirhr098@yahoo.com>
License: MIT License
Classifier: License :: OSI Approved :: MIT License
Classifier: Operating System :: OS Independent
Classifier: Programming Language :: Python :: 3
Requires-Python: >=3.8
